{
    "$schema": "https://schema.management.azure.com/schemas/2015-01-01/deploymentParameters.json#",
    "contentVersion": "1.0.0.0",
    "parameters": {
        "subscriptionId": {
            "value": "Redacted"
        },
        "name": {
            "value": "rss-feed-to-twitter"
        },
        "location": {
            "value": "Central US"
        },
        "hostingEnvironment": {
            "value": ""
        },
        "hostingPlanName": {
            "value": "ASP-rss-feed-to-twitter"
        },
        "serverFarmResourceGroup": {
            "value": "rss-feed-to-twitter"
        },
        "alwaysOn": {
            "value": true
        },
        "sku": {
            "value": "Basic"
        },
        "skuCode": {
            "value": "B1"
        },
        "workerSize": {
            "value": "0"
        },
        "workerSizeId": {
            "value": "0"
        },
        "numberOfWorkers": {
            "value": "1"
        },
        "currentStack": {
            "value": "dotnetcore"
        },
        "phpVersion": {
            "value": "OFF"
        },
        "errorLink": {
            "value": "https://rss-feed-to-twitter.scm.azurewebsites.net/detectors?type=tools&name=eventviewer"
        }
    }
}